{
  "sceneResX": 256,
  "sceneResY": 256,
  "sceneResZ": 31,
  "probeRays": 100000,
  "spp": 160,
  "gifOut": "./gifs/cells.gif",
  "gifDelay": 8,
  "gamma": 0.8,
  "scene": {
    "center": { "X": 0, "Y": 0, "Z": 0, "W": 0 },
    "width": 2.0,
    "height": 2.0,
    "depth": 2.0,
    "maxBounces": 28
  },
  "lights": [
    {
      "origin":    { "X": 0.0, "Y": 0.0, "Z": 0.0, "W": 1.0 },
      "direction": { "X": 0.0, "Y": 0.0, "Z": 0.0, "W": -1.0 },
      "color":     { "R": 1.0, "G": 1.0, "B": 1.0 },
      "angleDeg":  40.0
    }
  ],
  "cells16": [
    {
      "center": { "X": 0.20, "Y": 0.00, "Z": 0.00, "W": 0.20 },
      "scale": { "X": 0.2, "Y": 0.2, "Z": 0.2, "W": 0.2 },
      "rotDeg": { "xy": 5, "xz": -10, "xw": 10, "yz": -5, "yw": 15, "zw": -15 },
      "color":   { "R": 0.10, "G": 0.00, "B": 0.00 },
      "reflect": { "R": 0.20, "G": 0.20, "B": 0.20 },
      "refract": { "R": 0.70, "G": 0.70, "B": 0.70 },
      "ior":     { "R": 1.28, "G": 1.32, "B": 1.36 }
    }
  ],
  "cells24": [
    {
      "center": { "X": -0.20, "Y": 0.00, "Z": 0.20, "W": 0.20 },
      "scale": { "X": 0.2, "Y": 0.2, "Z": 0.2, "W": 0.2 },
      "rotDeg": { "xy": 15, "xz": -10, "xw": 5, "yz": 0, "yw": 0, "zw": 10 },
      "color":   { "R": 0.00, "G": 0.10, "B": 0.00 },
      "reflect": { "R": 0.20, "G": 0.20, "B": 0.20 },
      "refract": { "R": 0.70, "G": 0.70, "B": 0.70 },
      "ior":     { "R": 1.30, "G": 1.33, "B": 1.36 }
    }
  ]
}

